pyuspsvalidator/__init__.py
pyuspsvalidator/webtools.py
pyuspsvalidator-0.0.4.dist-info/LICENSE
pyuspsvalidator-0.0.4.dist-info/METADATA
pyuspsvalidator-0.0.4.dist-info/WHEEL
pyuspsvalidator-0.0.4.dist-info/top_level.txt
pyuspsvalidator-0.0.4.dist-info/RECORD
