Metadata-Version: 2.1
Name: pyuspsvalidator
Version: 0.0.4
License-File: LICENSE
Requires-Dist: requests >=2.31.0
